MANIFEST.in
setup.py
gftp/README.md
gftp/__init__.py
gftp/conn.py
gftp/downloader.py
gftp.egg-info/PKG-INFO
gftp.egg-info/SOURCES.txt
gftp.egg-info/dependency_links.txt
gftp.egg-info/requires.txt
gftp.egg-info/top_level.txt