Metadata-Version: 2.1
Name: gftp
Version: 0.0.5
Summary: 一个 ftp 便捷工具包
Home-page: https://github.com/Leviathangk/gftp
Author: 郭一会儿
Author-email: 1015295213@qq.com
License: MIT Licence
Keywords: ftp
Platform: any
